vtjson/__init__.py
vtjson/py.typed
vtjson/vtjson.py
vtjson-2.2.7.dist-info/licenses/AUTHORS
vtjson-2.2.7.dist-info/licenses/LICENSE
vtjson-2.2.7.dist-info/METADATA
vtjson-2.2.7.dist-info/WHEEL
vtjson-2.2.7.dist-info/top_level.txt
vtjson-2.2.7.dist-info/RECORD
