Metadata-Version: 2.4
Name: vtjson
Version: 2.2.7
Summary: An easy to use validation library compatible with Python type annotations
Author-email: Michel Van den Bergh <michel.vandenbergh@uhasselt.be>
Project-URL: Homepage, https://github.com/vdbergh/vtjson
Project-URL: Bug Tracker, https://github.com/vdbergh/vtjson/issues
Classifier: Programming Language :: Python :: 3
Classifier: License :: OSI Approved :: MIT License
Classifier: Operating System :: OS Independent
Requires-Python: >=3.7
License-File: LICENSE
License-File: AUTHORS
Requires-Dist: dnspython
Requires-Dist: email_validator
Requires-Dist: idna
Requires-Dist: python-magic
Requires-Dist: typing_extensions
Dynamic: license-file
